[
  {
    "line": 1,
    "elements": [
      {
        "start_timestamp": "2021-07-08T21:08:22.901Z",
        "before": [
          {
            "result": {
              "duration": 3838000000,
              "status": "passed"
            },
            "match": {
              "location": "stepDef.hook.openBrowser()"
            }
          }
        ],
        "line": 4,
        "name": "verify place holder for userName and Password",
        "description": "",
        "id": "signup;verify-place-holder-for-username-and-password",
        "type": "scenario",
        "keyword": "Scenario",
        "steps": [
          {
            "result": {
              "duration": 43000000,
              "status": "passed"
            },
            "line": 5,
            "name": "I am at TalentTek",
            "match": {
              "location": "stepDef.signup_step.iAmAtTalentTek()"
            },
            "keyword": "Given "
          },
          {
            "result": {
              "duration": 2223000000,
              "status": "passed"
            },
            "line": 6,
            "name": "I verify there is placeHolder for userName and Password",
            "match": {
              "location": "stepDef.signup_step.iVerifyThereIsPlaceHolderForUserNameAndPassword()"
            },
            "keyword": "And "
          },
          {
            "result": {
              "duration": 116000000,
              "status": "passed"
            },
            "line": 7,
            "name": "I verify email should be unit",
            "match": {
              "location": "stepDef.signup_step.iVerifyEmailShouldBeUnit()"
            },
            "keyword": "And "
          }
        ],
        "tags": [
          {
            "name": "@loginPlaceHolder"
          }
        ]
      }
    ],
    "name": "Signup",
    "description": "",
    "id": "signup",
    "keyword": "Feature",
    "uri": "file:src/test/java/FeatureFiles/signup.feature",
    "tags": []
  }
]